eod2pd/__init__.py
eod2pd/eod2pddownloader.py
eod2pd/eod2pddownloadercallable.py
eod2pd/utils.py
eod2pd-0.3.1.1.dist-info/METADATA
eod2pd-0.3.1.1.dist-info/WHEEL
eod2pd-0.3.1.1.dist-info/top_level.txt
eod2pd-0.3.1.1.dist-info/RECORD
